openjudge/__init__.py
openjudge/auth.py
openjudge/cli.py
openjudge/core.py
openjudge/default_interface.py
openjudge/server.py
openjudge/utils.py
openjudge/worker.py
openjudge/wrappers.json
openjudge/staticfiles/Chart.min.js
openjudge/staticfiles/jquery-3.2.1.min.js
openjudge/staticfiles/js.cookie.min.js
openjudge/staticfiles/main.css
openjudge/staticfiles/main.js
openjudge/staticfiles/showdown.min.js
openjudge/templates/home.html
openjudge-3.0.5.dist-info/METADATA
openjudge-3.0.5.dist-info/RECORD
openjudge-3.0.5.dist-info/WHEEL
openjudge-3.0.5.dist-info/entry_points.txt
openjudge-3.0.5.dist-info/top_level.txt
