Metadata-Version: 2.1
Name: openjudge
Version: 3.0.5
Summary: LAN Programming Contest Judging Program
Home-page: http://github.com/theSage21/openJudge
Author: Arjoonn Sharma
Author-email: arjoonn.94@gmail.com
License: MIT
Keywords: openjudge,lan,programming,programming,contest
Platform: UNKNOWN
Requires-Dist: motor
Requires-Dist: aiohttp
Requires-Dist: aiohttp-jinja2
Requires-Dist: aiohttp-cors
